minorg/MINORg.py
minorg/MINORgCLI.py
minorg/__init__.py
minorg/annotation.py
minorg/blast.py
minorg/console.py
minorg/constants.py
minorg/display.py
minorg/dynamic_logger.py
minorg/extend_reference.py
minorg/extract_homologue.py
minorg/fasta.py
minorg/filter_grna.py
minorg/functions.py
minorg/generate_grna.py
minorg/grna.py
minorg/index.py
minorg/log.py
minorg/mafftcommandline_add.py
minorg/minimum_set.py
minorg/minimum_set_legacy.py
minorg/minweight_sc.py
minorg/ot_regex.py
minorg/pam.py
minorg/parse_config.py
minorg/reference.py
minorg/searchio.py
minorg/untrack/filter_grna.py
minorg-0.2.3.4a0.dist-info/LICENSE
minorg-0.2.3.4a0.dist-info/METADATA
minorg-0.2.3.4a0.dist-info/WHEEL
minorg-0.2.3.4a0.dist-info/entry_points.txt
minorg-0.2.3.4a0.dist-info/top_level.txt
minorg-0.2.3.4a0.dist-info/RECORD
