Metadata-Version: 2.1
Name: minorg
Version: 0.2.3.4a0
Summary: Generate minimum gRNA set for multiple non-reference genomes
Home-page: https://github.com/rlrq/MINORg
Author: Rachelle R.Q. Lee
Author-email: rachelle.rq.lee@gmail.com
License: UNKNOWN
Project-URL: Bug Tracker, https://github.com/rlrq/MINORg/issues
Platform: UNKNOWN
Classifier: Programming Language :: Python :: 3
Classifier: Operating System :: OS Independent
Requires-Python: >=3.6
License-File: LICENSE
Requires-Dist: biopython (==1.79)
Requires-Dist: pybedtools (==0.9.0)
Requires-Dist: pyfaidx (==0.6.4)
Requires-Dist: regex
Requires-Dist: typer (==0.4.0)
Requires-Dist: multiprocess (==0.70.12.2)
